karoo_gp/__init__.py
karoo_gp/base_class.py
karoo_gp/pause.py
karoo_gp/files/coefficients.csv
karoo_gp/files/data_CLASSIFY.csv
karoo_gp/files/data_MATCH.csv
karoo_gp/files/data_PLAY.csv
karoo_gp/files/data_REGRESS.csv
karoo_gp/files/operators_CLASSIFY.csv
karoo_gp/files/operators_MATCH.csv
karoo_gp/files/operators_PLAY.csv
karoo_gp/files/operators_REGRESS.csv
karoo_gp-2.4.1.data/scripts/karoo-gp.py
karoo_gp-2.4.1.dist-info/LICENSE.md
karoo_gp-2.4.1.dist-info/METADATA
karoo_gp-2.4.1.dist-info/WHEEL
karoo_gp-2.4.1.dist-info/top_level.txt
karoo_gp-2.4.1.dist-info/RECORD
