Metadata-Version: 2.1
Name: karoo-gp
Version: 2.4.1
Summary: Use Genetic Programming for Classification and Symbolic Regression
Home-page: https://github.com/kstaats/karoo_gp
Author: Kai Staats
Author-email: github@overthesun.com
License: MIT
Project-URL: Documentation, https://github.com/kstaats/karoo_gp/blob/master/Karoo_GP_User_Guide.pdf
Project-URL: Source, https://github.com/kstaats/karoo_gp
Project-URL: Tracker, https://github.com/kstaats/karoo_gp/issues
Classifier: Programming Language :: Python :: 3
Classifier: Programming Language :: Python :: 3 :: Only
Classifier: License :: OSI Approved :: MIT License
Classifier: Operating System :: OS Independent
Classifier: Topic :: Scientific/Engineering
Classifier: Topic :: Scientific/Engineering :: Artificial Intelligence
Classifier: Intended Audience :: Science/Research
Classifier: Intended Audience :: Education
Classifier: Intended Audience :: Developers
Requires-Python: >=3
License-File: LICENSE.md
Requires-Dist: numpy
Requires-Dist: sklearn
Requires-Dist: sympy
Requires-Dist: tensorflow
